setup.py
src/apitestUtils/__init__.py
src/apitestUtils/config.py
src/apitestUtils/excelUtils.py
src/apitestUtils/fakerUtils.py
src/apitestUtils/reportUtils.py
src/apitestUtils/requestsUtils.py
src/apitestUtils/resultUtils.py
src/apitesttool.egg-info/PKG-INFO
src/apitesttool.egg-info/SOURCES.txt
src/apitesttool.egg-info/dependency_links.txt
src/apitesttool.egg-info/requires.txt
src/apitesttool.egg-info/top_level.txt