Metadata-Version: 1.0
Name: apitesttool
Version: 1.0.1
Summary: 接口测试工具
Home-page: https://github.com/JiChaoSong/ApiTestTool.git
Author: jichaosong
Author-email: jichaosong@outlook.com
License: UNKNOWN
Platform: UNKNOWN
